{
  "cards": [
    {
      "id": 6,
      "title": "Ir na padaria",
      "description": "Tomar café, comprar 10 pães, leite, manteiga e pão de queijo"
    },
    {
      "id": 7,
      "title": "Buscar remédio",
      "description": "Ir até a farmácia aqui no ponto final da padaria e comprar remédio para dor de cabeça."
    },
    {
      "id": 8,
      "title": "Hj eu vou a feira",
      "description": "Comprar frutas"
    },
    {
      "id": 9,
      "title": "hj vou a feira",
      "description": "comprar banana"
    },
    {
      "id": 10,
      "title": "Fzer uma teste",
      "description": "fazendo um teste"
    },
    {
      "id": 11,
      "title": "arcenio souza",
      "description": "fazer almoço amanhã"
    },
    {
      "id": 12,
      "title": "arcenio souza",
      "description": "fazer almoço amanhã"
    },
    {
      "id": 13,
      "title": "arcenio souza",
      "description": "fazer almoço amanhã"
    },
    {
      "id": 14,
      "title": "arcenio souza",
      "description": "fazer almoço amanhã"
    }
  ],
  "notes": [
    {
      "id": 1,
      "title": "Senha do wifi",
      "description": "sjjaiwu@1254522"
    },
    {
      "0": {
        "id": 1,
        "title": "Senha do wifi",
        "description": "sjjaiwu@1254522"
      },
      "title": "aaaaa",
      "description": "aaaaaaa",
      "id": 2
    }
  ]
}
